{
  "id": "auto_show",
  "name": "车展策划方案",
  "description": "适合汽车展会、车展活动的策划方案PPT",
  "version": "1.0.0",
  "theme": {
    "primary": "FA2F1F",
    "secondary": "002D6B"
  },
  "pages": [
    {
      "type": "cover",
      "title": "封面",
      "mainTitle": "智界汽车",
      "subtitle": "2025 上海国际车展策划方案",
      "date": "2025年4月23日-5月2日",
      "location": "上海国家会展中心 7.1H馆",
      "brand": "HUAWEI 鸿蒙智行"
    },
    {
      "type": "toc",
      "title": "目录",
      "items": [
        { "title": "项目背景与目标" },
        { "title": "车展概况" },
        { "title": "展位设计" },
        { "title": "活动规划" },
        { "title": "产品展示" },
        { "title": "传播策略" },
        { "title": "媒体邀请" },
        { "title": "执行时间表" },
        { "title": "团队分工" },
        { "title": "预算概览" }
      ]
    },
    {
      "type": "content",
      "title": "项目背景与目标",
      "sectionNum": "01",
      "sections": [
        {
          "title": "项目背景",
          "content": [
            "智界品牌累计订单突破13万台",
            "签约刘亦菲为品牌大使",
            "R7增程版于上海车展正式发布",
            "智能驾驶技术成为核心竞争差异化要素"
          ]
        },
        {
          "title": "核心目标",
          "content": [
            "提升智界品牌高端智能电动车市场认知度",
            "展示R7增程版+新S7 Ultra运动版",
            "收集意向客户信息 ≥8,000 组",
            "媒体曝光量 ≥3亿次"
          ]
        }
      ],
      "kpis": [
        { "value": "13万+", "label": "累计订单" },
        { "value": "8,000+", "label": "潜客收集" },
        { "value": "15万+", "label": "参展人流" },
        { "value": "3亿+", "label": "媒体曝光" }
      ]
    },
    {
      "type": "content",
      "title": "车展概况",
      "sectionNum": "02",
      "sections": [
        {
          "title": "展会信息",
          "content": [
            "展会名称：2025第二十一届上海国际汽车工业展览会",
            "媒体日：2025年4月23日-24日",
            "公众日：2025年4月25日-5月2日",
            "地点：上海国家会展中心（虹桥）",
            "展位：7.1号馆 · 7A05展位（800㎡）"
          ]
        }
      ]
    },
    {
      "type": "cards",
      "title": "展位设计",
      "sectionNum": "03",
      "cards": [
        {
          "title": "A区",
          "tag": "品牌展示区 200㎡",
          "description": "核心车型+技术展示",
          "features": [
            "巨型LED屏幕",
            "华为ADS智驾演示",
            "品牌故事展示"
          ]
        },
        {
          "title": "B区",
          "tag": "试乘体验区 300㎡",
          "description": "沉浸式智能驾驶体验",
          "features": [
            "专业试乘赛道",
            "安全陪驾团队",
            "预约试驾系统"
          ]
        },
        {
          "title": "C区",
          "tag": "洽谈区 150㎡",
          "description": "商务洽谈+咖啡休闲",
          "features": [
            "半私密设计",
            "专属接待服务",
            "咖啡茶点供应"
          ]
        },
        {
          "title": "D区",
          "tag": "互动打卡区 150㎡",
          "description": "AR拍照+社交传播",
          "features": [
            "刘亦菲代言专区",
            "社交分享互动",
            "精美礼品赠送"
          ]
        }
      ]
    },
    {
      "type": "cards",
      "title": "产品展示",
      "sectionNum": "05",
      "cards": [
        {
          "title": "智界R7",
          "tag": "增程版",
          "description": "纯电中大型SUV",
          "price": "29.98万-31.98万",
          "features": [
            "53.4kWh大电池",
            "华为DriveONE四驱",
            "360km纯电续航",
            "综合续航超1500km"
          ]
        },
        {
          "title": "智界S7",
          "tag": "Ultra运动版",
          "description": "纯电中大型轿车",
          "price": "31.98万",
          "features": [
            "零百3.3秒",
            "麋鹿测试83.1km/h",
            "华为ADS 3.0",
            "鸿蒙座舱4.0"
          ]
        },
        {
          "title": "智界R7",
          "tag": "纯电版",
          "description": "纯电中大型SUV",
          "price": "21.99万-28.99万",
          "features": [
            "800V超充",
            "华为途灵平台",
            "ADS 3.0智驾",
            "零百4.9秒"
          ]
        }
      ]
    },
    {
      "type": "timeline",
      "title": "执行时间表",
      "sectionNum": "08",
      "phases": [
        {
          "month": "2月",
          "name": "筹备期",
          "tasks": [
            "团队组建与分工",
            "展位设计定稿",
            "刘亦菲档期确认",
            "媒体名单确认"
          ]
        },
        {
          "month": "3月",
          "name": "准备期",
          "tasks": [
            "物料制作启动",
            "KOL排期确定",
            "媒体邀请函发送",
            "车辆运输安排"
          ]
        },
        {
          "month": "4月初",
          "name": "搭建期",
          "tasks": [
            "展位搭建进场",
            "设备调试",
            "刘亦菲彩排",
            "媒体签到准备"
          ]
        },
        {
          "month": "4/23-30",
          "name": "执行期",
          "tasks": [
            "媒体日发布",
            "公众日运营",
            "每日数据复盘",
            "刘亦菲见面会"
          ]
        },
        {
          "month": "5月",
          "name": "收尾期",
          "tasks": [
            "数据总结报告",
            "客户转化跟踪",
            "项目复盘会议",
            "下期预告发布"
          ]
        }
      ]
    },
    {
      "type": "content",
      "title": "预算概览",
      "sectionNum": "10",
      "sections": [
        {
          "title": "展位租赁与搭建",
          "content": ["320万 · 800㎡展位设计施工"]
        },
        {
          "title": "刘亦菲代言合作",
          "content": ["200万 · 出场费+专属活动"]
        },
        {
          "title": "媒体传播投放",
          "content": ["180万 · KOL/广告/直播"]
        },
        {
          "title": "活动策划执行",
          "content": ["80万 · 发布会/明星活动"]
        },
        {
          "title": "车辆运输保障",
          "content": ["50万 · 展车运输/维护"]
        },
        {
          "title": "应急预备金",
          "content": ["70万 · 不可预见费用"]
        }
      ],
      "total": "900万"
    },
    {
      "type": "end",
      "title": "结束页",
      "mainText": "感谢观看",
      "subText": "THANK YOU",
      "brand": "HUAWEI Zhijie · 2025 Shanghai Auto Show"
    }
  ]
}
